models/__init__.py
models/coin_model.py
models/common_model.py
models/eventnews_model.py
models/investement_model.py
models/realtimedata_model.py
models/score_model.py
models/traderecord_model.py
models/user_model.py
valueinvesting_models-0.1.0.dist-info/LICENSE
valueinvesting_models-0.1.0.dist-info/METADATA
valueinvesting_models-0.1.0.dist-info/WHEEL
valueinvesting_models-0.1.0.dist-info/top_level.txt
valueinvesting_models-0.1.0.dist-info/RECORD
